{"filename":"SRC_20대_제346회_제3차_소위원회_보건복지위원회-예산결산심사소위원회_0008(046570).xlsx",
"original":"http://likms.assembly.go.kr/record/mhs-10-040-0040.do?conferNum=046570&fileType=PDF",
"id":"046570",
"date":"2016년10월28일(금)",
"conference_number":"046570",
"question_number":"0008",
"meeting_name":"소위원회",
"generation_number":"20",
"committee_name":"보건복지위원회-예산결산심사소위원회",
"meeting_number":"제346회",
"session_number":"제3차",
"agenda":"1. 2017년도 예산안(계속)가. 보건복지부 소관2. 2017년도 기금운용계획안(계속)가. 보건복지부 소관",
"law":"2017년도 예산안;2017년도 기금운용계획안",
"qna_type":"추출형",
"context":"327페이지입니다.  육아종합센터에 상담전문요원을 배치하는 예산을 현재 예산안보다 추가로 배치하자는 의견으로 9억 9300만 원 증액 의견이 있습니다. 상담전문요원 지원은 저희가 광역까지 지원하고 시군구에 또 지원을 시작하게 되면 새로운 지원 방식이 시작되는 거라 이것은 수용하기 어렵다는 말씀 드리겠습니다.",
"context_learn":"지방자치단체나 정부 부처의 복지 분야 예산을 다루고 있는 중이신 것으로 보입니다. 질문 내용을 기반으로 한 상황의 가상적 맥락을 이해하고 세부적으로 설명드리겠습니다. 배경:육아종합센터는 부모와 어린이를 위한 다양한 서비스를 제공하는 기관입니다. 여기에는 상담 서비스, 양육 정보 및 리소스, 아동 돌봄 프로그램 등이 포함됩니다. 한 지역 또는 정부 내에서 의견이 제시됐는데, 그것은 육아종합센터에 상담전문요원을 추가로 배치하자는 것입니다. 증액 제안:해당 제안에 따르면 상담전문요원을 추가로 배치하기 위해 9억 9300만 원의 추가 예산을 배정하려고 합니다. 이 추가 예산이 승인된다면, 육아종합센터는 내부 자원을 강화하여 보다 효과적인 상담 서비스를 제공할 수 있을 것입니다. 상담전문요원이 더 많이 있으면 부모나 양육자들이 경험하는 다양한 어려움에 대해 더 전문적이고 심층적인 지원을 받을 수 있습니다. 복지부의 입장:그러나 복지부는 이 증액 제안을 수용하기 어렵다는 입장을 표명하였습니다. 이는 새로운 지원 방식을 도입하는 것이 현재 상황에서 어렵거나 불가능하다는 것을 암시합니다. 이것은 예산 우선순위, 현 상태에서의 충분한 자원의 부족, 기존 프로그램의 효율성 평가 또는 다른 행정적, 정치적 결정과 관련이 있을 수 있습니다. 효과 및 영향:만약 복지부가 이 제안을 수용하지 않는다면, 육아종합센터는 추가 상담전문요원을 배치하는 데 필요한 예산을 확보하지 못할 것입니다. 이는 육아종합센터의 서비스 용량에 영향을 미치며, 이는 다시 부모와 어린이가 제공받는 지원 수준에 영향을 줄 수 있습니다. 결론:이 상황에서는 예산 증액의 필요성과 복지부의 입장 사이에 간극이 존재합니다. 관련 당사자들은 토론을 통해 해결책을 모색할 필요가 있으며, 더 나은 양육 환경과 가족의 복지 향상을 위한 다른 대안이나 재원 조달 방안을 고려해야 할 것입니다.",
"context_summary":{"summary_q":"육아종합센터에 상담전문요원 추가 지원을 위한 9억 9300만 원 증액 의견이 있습니다. 이에 대한 복지부의 입장은 어떠한가요?",
"summary_a":"복지부는 육아종합센터에 상담전문요원 추가 지원에 대한 9억 9300만 원의 증액 의견을 수용하기 어렵다는 입장을 표명하고 있습니다. 새로운 지원 방식의 도입이 어려운 상황임을 감안하고 있습니다."},
"questioner_name":"김승기",
"questioner_ID":" ",
"questioner_ISNI":" ",
"questioner_affiliation":"",
"questioner_position":"수석전문위원",
"question":{"tag":"87",
"comment":"327페이지입니다.  육아종합센터에 상담전문요원을 배치하는 예산을 현재 예산안보다 추가로 배치하자는 의견으로 9억 9300만 원 증액 의견이 있습니다.",
"keyword":"육아종합센터, 상담전문요원, 배치, 예산, 예산안, 추가, 의견, 증액"},
"answerer_name":"방문규",
"answerer_ID":" ",
"answerer_ISNI":" ",
"answerer_affiliation":"보건복지부",
"answerer_position":"차관",
"answer":{"tag":"89",
"comment":"상담전문요원 지원은 저희가 광역까지 지원하고 시군구에 또 지원을 시작하게 되면 새로운 지원 방식이 시작되는 거라 이것은 수용하기 어렵다는 말씀 드리겠습니다.",
"keyword":"상담전문요원, 광역, 지원, 시군구, 시작, 방식, 수용"}}