{"filename":"SRC_20대_제347회_제1차_소위원회_기획재정위원회-경제재정소위원회_0002(046835).xlsx",
"original":"http://likms.assembly.go.kr/record/mhs-10-040-0040.do?conferNum=046835&fileType=PDF",
"id":"046835",
"date":"2016년12월21일(수)",
"conference_number":"046835",
"question_number":"0002",
"meeting_name":"소위원회",
"generation_number":"20",
"committee_name":"기획재정위원회-경제재정소위원회",
"meeting_number":"제347회",
"session_number":"제1차",
"agenda":"1. 공공기관의 운영에 관한 법률 일부개정법률안(박남춘 의원 대표발의)(계속) 2. 공공기관의 운영에 관한 법률 일부개정법률안(이상민 의원 대표발의)(계속) 3. 공공기관의 운영에 관한 법률 일부개정법률안(오세정 의원 대표발의)(계속) 4. 공공기관의 운영에 관한 법률 일부개정법률안(박대출 의원 대표발의)(계속) 5. 공공기관의 운영에 관한 법률 일부개정법률안(신용현 의원 대표발의)(계속) 6. 공공기관의 운영에 관한 법률 일부개정법률안(박광온 의원 대표발의)(계속) 7. 공공기관의 운영에 관한 법률 일부개정법률안(심상정 의원 대표발의)(의안번호 1124)(계속) 8. 공공기관의 운영에 관한 법률 일부개정법률안(박찬대 의원 대표발의)(계속) 9. 공공기관의 운영에 관한 법률 일부개정법률안(박정 의원 대표발의)(계속)10. 공공기관의 운영에 관한 법률 일부개정법률안(김삼화 의원 대표발의)(계속)11. 공공기관의 운영에 관한 법률 일부개정법률안(백혜련 의원 대표발의)(계속)12. 공공기관의 운영에 관한 법률 일부개정법률안(심상정 의원 대표발의)(의안번호 1779)(계속)13. 공공기관의 운영에 관한 법률 일부개정법률안(이춘석 의원 대표발의)(계속)14. 공공기관의 운영에 관한 법률 일부개정법률안(천정배 의원 대표발의)(계속)15. 공공기관의 운영에 관한 법률 일부개정법률안(이언주 의원 대표발의)(계속)16. 공공기관의 학력차별금지 및 기회균등보장에 관한 법률안(김해영 의원 대표발의)(계속)17. 국가균형발전 특별법 일부개정법률안(박찬대 의원 대표발의)(계속)18. 국가균형발전 특별법 일부개정법률안(김광수 의원 대표발의)(계속)19. 국가를 당사자로 하는 계약에 관한 법률 일부개정법률안(김경협 의원 대표발의)(계속)20. 국가를 당사자로 하는 계약에 관한 법률 일부개정법률안(박명재 의원 대표발의)(계속)21. 국가재정법 일부개정법률안(박명재 의원 대표발의)(계속)22. 국가재정법 일부개정법률안(우원식 의원 대표발의)(계속)23. 국가재정법 일부개정법률안(송석준 의원 대표발의)(계속)24. 국가재정법 일부개정법률안(이우현 의원 대표발의)(계속)25. 국가재정법 일부개정법률안(심상정 의원 대표발의)(계속)26. 국가재정법 일부개정법률안(채이배 의원 대표발의)(계속)27. 국가재정법 일부개정법률안(유동수 의원 대표발의)(계속)28. 국가재정법 일부개정법률안(김현미 의원 대표발의)(의안번호 890)(계속)29. 국가재정법 일부개정법률안(주승용 의원 대표발의)(의안번호 926)(계속)30. 국가재정법 일부개정법률안(주호영 의원 대표발의)(계속)31. 국가재정법 일부개정법률안(이현재 의원 대표발의)(의안번호 1005)(계속)32. 국가재정법 일부개정법률안(유재중 의원 대표발의)(계속)33. 국가재정법 일부개정법률안(강훈식 의원 대표발의)(계속)34. 국가재정법 일부개정법률안(김광수 의원 대표발의)(계속)35. 국가재정법 일부개정법률안(김현미 의원 대표발의)(의안번호 1219)(계속)36. 국가재정법 일부개정법률안(김태년 의원 대표발의)(계속)37. 국가재정법 일부개정법률안(박정 의원 대표발의)(계속)38. 국가재정법 일부개정법률안(서영교 의원 대표발의)(계속)39. 국가재정법 일부개정법률안(박홍근 의원 대표발의)(계속)40. 국가재정법 일부개정법률안(윤호중 의원 대표발의)(의안번호 1447)(계속)41. 국가재정법 일부개정법률안(김해영 의원 대표발의)(계속)42. 국가재정법 일부개정법률안(김태흠 의원 대표발의)(계속)43. 국가재정법 일부개정법률안(윤호중 의원 대표발의)(의안번호 1615)(계속)44. 국가재정법 일부개정법률안(김민기 의원 대표발의)(계속)45. 국가재정법 일부개정법률안(한선교 의원 대표발의)(계속)46. 국가재정법 일부개정법률안(김종민 의원 대표발의)(의안번호 1985)(계속)47. 국가재정법 일부개정법률안(안상수 의원 대표발의)(계속)48. 국가재정법 일부개정법률안(주승용 의원 대표발의)(의안번호 2061)(계속)49. 국가재정법 일부개정법률안(김종민 의원 대표발의)(의안번호 2134)(계속)50. 국가재정법 일부개정법률안(노웅래 의원 대표발의)(계속)51. 국가재정법 일부개정법률안(이현재 의원 대표발의)(의안번호 2485)(계속)52. 국가재정법 일부개정법률안(오영훈 의원 대표발의)(계속)53. 국가재정법 일부개정법률안(김종민 의원 대표발의)(의안번호 2715)(계속)54. 국가재정법 일부개정법률안(윤소하 의원 대표발의)(계속)55. 국가재정법 일부개정법률안(정세균 의원 대표발의)(계속)56. 국가채권 관리법 일부개정법률안(김해영 의원 대표발의)(계속)57. 국가회계법 일부개정법률안(유재중 의원 대표발의)(계속)58. 국가회계법 일부개정법률안(윤호중 의원 대표발의)(계속)59. 국가회계법 일부개정법률안(박광온 의원 대표발의)(계속)60. 국고금 관리법 일부개정법률안(김해영 의원 대표발의)(계속)61. 국유재산법 일부개정법률안(신경민 의원 대표발의)(계속)62. 국유재산법 일부개정법률안(김해영 의원 대표발의)(계속)63. 국유재산법 일부개정법률안(주광덕 의원 대표발의)(계속)64. 국유재산특례제한법 일부개정법률안(안규백 의원 대표발의)(계속)65. 국유재산특례제한법 일부개정법률안(유승희 의원 대표발의)(계속)66. 국유재산특례제한법 일부개정법률안(박주선 의원 대표발의)(계속)67. 국유재산특례제한법 일부개정법률안(원혜영 의원 대표발의)(계속)68. 국유재산특례제한법 일부개정법률안(추혜선 의원 대표발의)(계속)69. 국채법 일부개정법률안(박광온 의원 대표발의)(계속)70. 담배사업법 일부개정법률안(박맹우 의원 대표발의)(계속)71. 담배사업법 일부개정법률안(박명재 의원 대표발의)(계속)72. 담배사업법 일부개정법률안(최도자 의원 대표발의)(계속)73. 물품관리법 일부개정법률안(김해영 의원 대표발의)(계속)74. 보조금 관리에 관한 법률 일부개정법률안(김민기 의원 대표발의)(계속)75. 보조금 관리에 관한 법률 일부개정법률안(민홍철 의원 대표발의)(계속)76. 보조금 관리에 관한 법률 일부개정법률안(박광온 의원 대표발의)(계속)77. 보조금 관리에 관한 법률 일부개정법률안(박맹우 의원 대표발의)(계속)78. 보조금 관리에 관한 법률 일부개정법률안(이인영 의원 대표발의)(계속)79. 보조금 관리에 관한 법률 일부개정법률안(장석춘 의원 대표발의)(계속)80. 보조금 관리에 관한 법률 일부개정법률안(정부 제출)(계속)81. 부담금관리 기본법 일부개정법률안(이찬열 의원 대표발의)(계속)82. 부담금관리 기본법 일부개정법률안(심상정 의원 대표발의)(계속)83. 부담금관리 기본법 일부개정법률안(박정 의원 대표발의)(계속)84. 부담금관리 기본법 일부개정법률안(신동근 의원 대표발의)(계속)85. 부담금관리 기본법 일부개정법률안(김영춘 의원 대표발의)(계속)86. 사회적경제 기본법안(유승민 의원 대표발의)(계속)87. 사회적경제기본법안(윤호중 의원 대표발의)(계속)88. 공공기관의 사회적 가치 실현에 관한 기본법안(김경수 의원 대표발의)(계속)89. 서비스산업발전 기본법안(이명수 의원 대표발의)(계속)90. 외국환거래법 일부개정법률안(정부 제출)(계속)91. 조달사업에 관한 법률 일부개정법률안(추경호 의원 대표발의)(계속)92. 지역전략산업 육성을 위한 규제프리존의 지정과 운영에 관한 특별법안(이학재 의원 대표발의)(계속)93. 청년기본법안(신보라 의원 대표발의)(계속)94. 최고임금법안(심상정 의원 대표발의)(계속)95. 한국수출입은행법 일부개정법률안(박용진 의원 대표발의)(계속)96. 한국은행법 일부개정법률안(송영길 의원 대표발의)(계속)97. 한국은행법 일부개정법률안(김현미 의원 대표발의)(계속)98. 한국은행법 일부개정법률안(박광온 의원 대표발의)(의안번호 2405)(계속)99. 한국은행법 일부개정법률안(박광온 의원 대표발의)(의안번호 2718)(계속)",
"law":"공공기관의 운영에 관한 법률 일부개정법률안 ;공공기관의 학력차별금지 및 기회균등보장에 관한 법률안(김해영 의원 대표발의)(계속) ;국가균형발전 특별법 일부개정법률안 ;국가를 당사자로 하는 계약에 관한 법률 일부개정법률안 ;국가재정법 일부개정법률안 ;국가채권 관리법 일부개정법률안 ;국가회계법 일부개정법률안 ;국고금 관리법 일부개정법률안 ;국유재산법 일부개정법률안 ;국유재산특례제한법 일부개정법률안 ;국채법 일부개정법률안 ;담배사업법 일부개정법률안 ;물품관리법 일부개정법률안 ;보조금 관리에 관한 법률 일부개정법률안 ;부담금관리 기본법 일부개정법률안 ;사회적경제 기본법안 ;공공기관의 사회적 가치 실현에 관한 기본법안 ;서비스산업발전 기본법안 ;외국환거래법 일부개정법률안 ;조달사업에 관한 법률 일부개정법률안 ;지역전략산업 육성을 위한 규제프리존의 지정과 운영에 관한 특별법안;청년기본법안;최고임금법안;한국수출입은행법 일부개정법률안;한국은행법 일부개정법률안",
"qna_type":"추출형",
"context":"먼저 정부 측 설명해 주시기 바랍니다. 거기에 있는 통합관리망 주요 내용에 대한 PT 자료를 가지고 간단히 설명 올리겠습니다.  1페이지입니다.  통합관리망 개요입니다.  이 통합관리망은 보조사업을 원활하게 수행하고, 보조금 중복ㆍ부정 수급을 방지하기 위해서 2011년에 지금 현행 법에 반영되어 있는 그런 사항이 되겠습니다. 그래서 부정 방지의 목적과 그다음에 파생적으로 업무 효율화, 대국민 서비스의 개선을 목표로 추진을 하고 있습니다.  다음 페이지입니다.  목표 시스템의 구성도는 보조사업을 담당하는 해당 공무원과 보조사업자 그리고 일반 국민에 이르기까지 사용하게 되고 현재 보조사업 관리, 그다음에 집행 관리 등 55개의 기능을 수행하도록 되어 있습니다. 그리고 그중에서 집행과 관련된 25개 기능을 내년 1월 오픈 대상으로 지금 준비를 하고 있습니다.  다음 페이지입니다.  전체적인 업무 흐름도입니다.  보조금통합관리망은 보조금의 예산편성부터 대상자 선정, 집행, 정산ㆍ사후 관리 등 보조금의 라이프 사이클 전체를 관리하게 되고요. 사업 성격에 따라서 사업형과 급여형으로 달라지고……  그래서 먼저 사업형을 말씀드리면 그 해당 부처에서 공모를 올리게 됩니다, 저희 시스템을 통해서. 그러면 사업 신청을 받아서 적격자를 선정하는 심사를 거쳐서 교부 신청과 교부가 이루어지게 됩니다. 그렇게 되면 집행 단계에서는 영수증의 허위 증빙이라든가 중복 사용을 체크하기 위해서 유효성 검증을 국세청과 금융결제원과 연계해서 확인한 다음에 최종적으로 자금이 집행되고 집행 결과는 저희 DB에 관리되게 되겠습니다.  그리고 기초생보와 같은 급여형 사업에 대해서는 이미 현재 자체 시스템들이 갖춰져 있습니다. 그래서 그 시스템을 통해서 자격 검증이 이루어지게 되고 최종적으로 결정된 자격 대상자에 대한 집행 내역만 저희 시스템에 확보되는 그런 내용이 되겠습니다.  다음 페이지입니다.  공모사업을 통한 자격 검증의 예시입니다.  해당 사업은 미래부 사업을 예시한 내용이 되겠습니다. 먼저 해당 사업을 담당하는 부처에서는 사업을 하게 되면 수급 기준과 제외 기준을 설정하게 됩니다. 그러면 해당 사항 중에서 온라인으로 검증한 사항에 대해서 항목으로 올리게 되고, 이런 부분들에 대해서 해당 기관에 저희가 자료를 확인하는 그런 절차를 갖게 됩니다. 그리고 해당 내용이 확인되면 저희가 따로 보관하지 않고 삭제하는 그런 상황이 되겠습니다.  그리고 정보의 축적에 관련해서 담당자가 해당하는 사업에 대해서만 조회가 가능하고, 기타 타 부처의 사업이라든가 이런 부분들은 접근 권한을 제한해서 할 수 없도록 이렇게 지금 관리를 하고 있습니다.  다음 페이지입니다.  현재 일부 자체 시스템을 가지고 있는 시스템과의 관련입니다.  대표적으로 행복e음이라는 시스템이 있는데 이 경우에 사업 대상자의 어떤 선정이나 이런 부분들은 말씀드린 대로 해당 시스템을 통해서 결정이 되고 급여 결정이 이루어지게 됩니다. 그렇게 되면 저희는 최종적인 집행 결과만, 누가 얼마 받았는지 이 내역만 저희 시스템에 반영되는 그런 내용이 되겠습니다.  다음 페이지 말씀드리겠습니다.  이렇게 축적되거나 관리되는 정보가 충분하게 보호될 수 있도록 개인정보 관리 방안에 대해서도 철저하게 준비를 했습니다. 기본적인 내용은 개인정보 보호법에 따라서 저희가 지침을 받아서 엄격하게 수행하고 있는 내용이 되겠고요.  주요 내용을 보면 저희 시스템 내에서 개인정보 관리를 할 때 암호화 처리를 하든가 데이터 표출 이런 부분에 있어서 개인정보가 식별되지 않도록 처리를 하고, 특히 그와 관련된 개인정보의 처리에 대한 접속 기록이라든가 이런 부분들을 기록으로 관리하고 주기적으로 감사를 해서 위험 행위가 발생하지 않도록 그렇게 관리를 하게 되겠습니다.  그리고 시스템 전체의 보안 관리에 대해서는 정보통신기반 보호법에 따라서 엄격하게 가장 강한 관리를 받도록 이렇게 되겠습니다.  다음 페이지 말씀드리겠습니다.  소위에서 주신 말씀과 전문가 의견을 감안해서 개인정보 보호 강화를 위해서 저희가 법안을 수정했습니다.   첫 번째로 개인정보 보호 관련해 가지고 법상 연계 대상의 시스템을 명시적으로 확대를 했습니다. 사회서비스전자바우처 시스템 등 이런 부분들을 추가로 반영을 좀 했고요.   그리고 불필요한 자료가 수집되지 않도록 소득, 재산과 같은 인적 자료 이런 부분들은 연계 대상에서 아예 제외되도록 명시적으로 명문화를 했습니다.   또한 외부기관의 어떤 불필요한 자료 요구를 제한할 수 있도록 제공하지 않도록 하기 위해서 예외 항목으로 명시된 경우 외에는 자료 제공을 하지 않도록 그렇게 저희가 지금 명문화를 했습니다.  또한 기재부장관이 보조금관리정보에 대해서 보다 엄격한 기술적ㆍ관리적 대책을 수립할 의무를 부과했습니다.   그리고 보조금법에 규정이 없는 경우를 제외하고는 개인정보 보호법에서 정하는 내용을 충실히 따르도록 이렇게 규정했습니다.  그리고 밑에 있는 내용이 되겠습니다마는 자격 검증 등에 활용된 그런 타 기관 보유 자료는 즉시 폐기를 원칙으로 하고, 특히 정보 주체의 어떤 동의 절차나 이런 부분들은 시행령 등에 반영해 가지고 개인정보 보호가 충실하게 이루어지도록 그렇게 준비를 하겠습니다.  다음 페이지는 참고자료로 보조금법과 타 법률의 개인정보 수집항목 비교고요.   그다음 페이지는 시스템 구축 후의 기대 효과입니다.  일부 자체 시스템이 있다 하더라도 사업 관리 범위를 보면 6.2%에 불과한 상황이고, 그래서 저희 시스템을 통해서 전체 사업이 관리되겠고요. 그리고 부정과 중복 수급 방지를 통해서 한 1조 원 정도의 재정 절감 효과가 기대되고 있습니다.  오늘 이 자리에는 일부 전문가뿐만 아니라 저희 사업을 총괄해서 관리를 해 왔던 김장훈 총괄 PM도 같이 와 있어서 답변을 충실하게 드리도록 하겠습니다.  이상입니다. 우리가 지난번 소위에서 지적한 내용에 대해서 설명을 쭉 들었고, 시스템상의 보완장치는 완벽하다라고는 할 수 없지만 최소한 지금 현재 가능한 충분한 조치가 취해져 있다는 그런 전문가들의 평가도 있었습니다.   또 지적사항에 대한 보조금법안 수정안을 정부가 마련했는데요.   수정 내용은 아직 보고 안 된 건가요? 수정 내용은 소위 심사자료에 다 있습니다. 우리가 지난번 소위에서 지적한 내용에 대해서 설명을 쭉 들었고, 시스템상의 보완장치는 완벽하다라고는 할 수 없지만 최소한 지금 현재 가능한 충분한 조치가 취해져 있다는 그런 전문가들의 평가도 있었습니다.   또 지적사항에 대한 보조금법안 수정안을 정부가 마련했는데요.   수정 내용은 아직 보고 안 된 건가요? 별도 자료는 뒤 페이지 보면 빨간색이 하나 있거든요. 이것은 더 추가를 하고자 하는 정부 의견입니다. 소위 심사자료 신ㆍ구 조문 대비표에 보면 101페이지부터 되어 있는 내용에 빨간 것 다 들어가 있습니다. 이것이 쭉 들어가 있는데 안 되어 있는 것이 있어요. 뭐냐 하면 벌칙 조항을 안 바꿨는데, 그러니까 제26조의6을 신설하면서 제26조의6 제2호부터 제4호까지 위반한 자에 대한 벌칙 조항은 들어가 있는데 수정의견에 있는 제26조의6 제2항 이하의 부분에 대해서는 처벌 조항이 없는 문제가 있네요. 여기에 대해서는…… 답변드리겠습니다.   지금 자료에 보시면 제26조의6 현재 있는 제2호에 ‘업무상 알게 된 보조금관리정보를 목적 외에 다른 용도로 사용하거나 다른 사람 또는 기관에 제공ㆍ누설하는 행위’ 이 부분에 대해서는 벌칙 조항이 있습니다. 이것은 보조금관리정보를 관리하는 그 경우에 대한 거고요.  신설된 제2항에 대한 부분은 기관에 대한 의무입니다. 그래서 이런 경우가 지금 국세기본법에도 규정되어 있는데 기관에 대한 부분은 따로 벌칙 조항이 지금 없습니다, 다른 입법에서도. 그래서 내용은 같지만 사실은 대상이 기관이기 때문에 기관에 대해서 부여하지 않고 있다는 말씀을 드릴 수 있겠습니다.",
"context_learn":"정부의 통합관리망에 대한 설명을 기반으로, 제안된 수정의견과 관련하여 약간의 혼란이 있어 보입니다. 통합관리망은 보조금의 중복 및 부정 수급을 방지하며 업무의 효율성과 대국민 서비스 개선을 목적으로 하고 있습니다. 주요 기능으로는 보조사업의 관리 및 집행과 관련된 여러 절차들을 포함하고 있으며, 정보의 보호 및 관리에 있어서도 철저한 준비와 보안 관리를 진행하고 있습니다. 그러나 제안된 수정의견 중 제26조의6의 제2항 이하 부분에 대한 처벌 조항이 빠져 있다는 지적이 있습니다. 이 조항은 기관에 대한 의무를 다루는 내용으로, 해당 기관이 보조금관리정보의 부적절한 사용, 제공, 누설을 하지 않도록 의무를 부여하는 것입니다. 현재 다른 입법 사례에서도 기관에 대한 벌칙 조항을 별도로 두지 않는 경우가 있으며, 이런 전례에 따라 벌칙 조항이 누락되었을 수 있습니다. 그러나 내용상으로는 기관의 의무 위반에 대한 벌칙 조항이 명시되어야 한다는 지적이 있으며, 이에 대해 해수부는 해당 기관에 대한 의무 위반 시 적절한 조치가 필요하다는 입장을 취하고 있습니다. 해수부는 제26조의6 제2항 이하 부분에 대한 벌칙 조항을 추가하는 것이 필요하다고 보고 있을 것이며, 이는 정보를 관리하고 보호하는 기관에 대한 책임을 더욱 명확하게 할 필요가 있음을 강조하는 것입니다. 이와 같이 수정의견에 대한 해수부의 입장이 요구되는 상황이며, 해당 부분에 대한 의견 수렴과 법적 조치에 대한 논의가 필요할 것으로 판단됩니다.",
"context_summary":{"summary_q":"현재 제안된 수정의견 중 제26조의6의 제2항 이하 부분에 대한 처벌 조항이 빠져 있는 문제가 있습니다. 해당 부분은 기관에 대한 의무를 다루는데, 이에 대한 벌칙 조항이 누락된 것으로 보입니다. 해수부는 이에 대한 어떤 입장을 가지고 있나요?",
"summary_a":"현재 제안된 수정의견에서 제26조의6의 제2항 이하 부분에 대한 처벌 조항이 빠져 있는 문제가 있으며, 해당 부분은 기관에 대한 의무를 다루는 것이므로 벌칙 조항을 추가하는 것이 필요하다는 해수부의 입장입니다."},
"questioner_name":"윤호중",
"questioner_ID":"7536",
"questioner_ISNI":"0000000463652364",
"questioner_affiliation":"",
"questioner_position":"위원",
"question":{"tag":"79",
"comment":"이것이 쭉 들어가 있는데 안 되어 있는 것이 있어요. 뭐냐 하면 벌칙 조항을 안 바꿨는데, 그러니까 제26조의6을 신설하면서 제26조의6 제2호부터 제4호까지 위반한 자에 대한 벌칙 조항은 들어가 있는데 수정의견에 있는 제26조의6 제2항 이하의 부분에 대해서는 처벌 조항이 없는 문제가 있네요. 여기에 대해서는……",
"keyword":"조항,   벌칙,    신설,   위반"},
"answerer_name":"윤병태",
"answerer_ID":" ",
"answerer_ISNI":" ",
"answerer_affiliation":"기획재정부",
"answerer_position":"보조금통합관리시스템추진단장",
"answer":{"tag":"81",
"comment":"답변드리겠습니다.   지금 자료에 보시면 제26조의6 현재 있는 제2호에 ‘업무상 알게 된 보조금관리정보를 목적 외에 다른 용도로 사용하거나 다른 사람 또는 기관에 제공ㆍ누설하는 행위’ 이 부분에 대해서는 벌칙 조항이 있습니다. 이것은 보조금관리정보를 관리하는 그 경우에 대한 거고요.  신설된 제2항에 대한 부분은 기관에 대한 의무입니다. 그래서 이런 경우가 지금 국세기본법에도 규정되어 있는데 기관에 대한 부분은 따로 벌칙 조항이 지금 없습니다, 다른 입법에서도. 그래서 내용은 같지만 사실은 대상이 기관이기 때문에 기관에 대해서 부여하지 않고 있다는 말씀을 드릴 수 있겠습니다.",
"keyword":"기관,  부분,  보조금관리정보,  벌칙,  조항,  경우,  답변,  자료"}}