{"filename":"SRC_20대_제354회_제1차_소위원회_국회운영위원회-예산결산심사소위원회_0006(047544).xlsx",
"original":"http://likms.assembly.go.kr/record/mhs-10-040-0040.do?conferNum=047544&fileType=PDF",
"id":"047544",
"date":"2017년11월13일(월)",
"conference_number":"047544",
"question_number":"0006",
"meeting_name":"소위원회",
"generation_number":"20",
"committee_name":"국회운영위원회-예산결산심사소위원회",
"meeting_number":"제354회",
"session_number":"제1차",
"agenda":"1. 2018년도 예산안(계속)다. 국회 소관",
"law":"",
"qna_type":"추출형",
"context":"5000만 원인가요? 5400으로 되어 있는데요? 그러면 5400만 원 수용하겠습니다. 1, 2, 3, 4번까지 가능하다는 거예요, 아니면…… 예, 4번까지입니다. 4번까지 중에서 다만 2번이 초과근무수당을 24시간으로 할지 33시간으로 할지인데 33시간으로 요구하신 것 같습니다. 다 의견이 같으세요?    (「예」 하는 위원 있음)   그러면 지금 현재 1번하고 2의 B하고 4번 이렇게 하면 21억 2400만 원 증액이 필요하다는 거고 거기에다가 향후에 상여금과 복리후생은 다른 직급에 있는 분들과 형평성을 감안해서 추가 반영한다, 이렇게 정리하면 되겠지요? 그게 언제 결정됩니까, 나머지 분들 것은? 그것도 아마 이번 예산심의 과정에서 논의될 거라고 보는데요, 그 부분은 아마도 예결위에서, 이 부분은 또 정부 쪽 기관들하고 같이 연계된 문제이기 때문에…… 36만 원 증액이잖아요, 그렇게 되면? 예. 어떻게 지급이 되는 겁니까? 그러니까 아까 말씀하신 KTX는 보통 선 지급 후 영수증 처리 형식이잖아요? 예. 그런데 그동안 KTX하고 코레일하고 협약을 통해서 약간 할인이 됐는데 이제는 할인 안 받고 앞으로 전액 처리하겠다, 이 말씀에 따라서 3억을 증액하자는 이야기시고. 그러니까 이것은 그동안 3억을 포함해서 총 얼마지요? 이것 그러면 그동안 KTX에만 해당됐던 건가요? KTX는 할인요금을 적용받아 왔고요. 이번에 SRT하고는 협의가 들어갔습니다. 그러니까 열차에만 해당되는 건가요? 예, 그렇습니다. 그러니까 열차에만 해당되는 건가요? 이것은 철도나 항공도 다 포함되는 거고요. 유류비까지 다 포함된 금액이 전체 13억 정도 되는데요. 예를 들면 수도권 195만 원으로 되어 있잖아요. 그러면 이 한도 안에서 지역 일정을 소화하거나 필요에 의해서 공무출장을 갔다 오거나 이런 게 KTX, 항공, 그다음에 차량 유지비 이게 포함된다는 말씀이시지요? 예. 지금 의원 1인당 공무수행출장비가 연 508만 원이라는 게 여기에 대중교통 KTX나 비행기 그리고 유류대 다 포함해서 508만 원인 것인가요? 예, 그렇습니다. 그런 건가요? 그런데 예전에는 이것을 사용하고, 그러니까 1인당 평균액이 있다 하더라도 사용 잔액이 남으면 그것을 재배정해 가지고…… 많이 이용하는 의원들이 있고 적게 이용하는 의원들이 있는 것 아니겠습니까? 그렇게 했던 것으로 제가 알고 있었는데 그게 제도가 바뀌었습니까? 그것은 바뀌지 않았는데요. 금년에는 여유 재원이…… 그런 건가요? 그런데 예전에는 이것을 사용하고, 그러니까 1인당 평균액이 있다 하더라도 사용 잔액이 남으면 그것을 재배정해 가지고…… 많이 이용하는 의원들이 있고 적게 이용하는 의원들이 있는 것 아니겠습니까? 그렇게 했던 것으로 제가 알고 있었는데 그게 제도가 바뀌었습니까? 운영지원과장입니다.  처음에 배정할 때 이게 예산이 13억 5000만 원입니다. 그래서 삼백 분으로 균일하게 나누면 원칙적으로 한 450만 원 정도 되고 13억 5000만 원이 소진이 되는데요. 연초에 배정을 할 때 불용률 등을 감안해 가지고 약 한 13% 정도를 추가로 의원님들께 배정을 해서 1인당 평균 배정액이 508만 원으로 미리 추가로 더 배정을 해서 집행을 하고 있습니다.   그래서 집행 잔액이 연말에 의원공무수행출장비는 거의 없다라고 보시면 될 것 같습니다. 저도 대전인데도 작년에 KTX 비용으로 나간 게 배정된 금액을 초과해서 정치자금, 이것으로 집행을 했는데요. 아무튼 대전인데도 그런데 좀 더 먼 데 KTX를 타시는 분들의 경우에는 상당히 마이너스가 많을 것이라고 저는 보입니다. 그래서 실비 차원의 이런 부분까지 너무 죄인처럼 스스로 자학하는, 이것은 아니지 않은가 이런 생각입니다. 위원장님, 참고로 일단 의원님들한테 이렇게 평균적으로 배분했을 때 남는 금액은 거의 없다고 보면 될 것 같고요. 또 저희가 의원님들이 의정활동 하시면서 추가로 요청하는 부분들이 있어서 매년 한 1억 7000 정도는 추가 배정을 합니다. 그래서 이것도 감안하셔야 되고 또 아까 처음에 차장님 말씀하셨던 할인율 폐지 부분 그런 것까지 포함하면 3억 이상은 편성이 되어야 의정활동이 원활히 될 것 같습니다. 예, 거기에 대해서 이견이 있는 것 같지는 않고요. 아까 말씀하신 것처럼 이게 혹시나 특권으로 비쳐질 소지가 없어야 되고 오히려 좀 더 정당한 의정활동에 대한, 그러니까 투명한 집행이라고 하는 것들이 따라졌으면 좋겠다는 취지 아니겠어요.   그러니까 그런 차원에서, 기존에 그렇게 할인율 받던 것을 안 받는 차원에서 예산이 추가적으로 3억 더 필요하다는 것에 대해서는 다 동의를 하실 것 같아요. 다만 그 집행에 있어서의 효율성이나 형평성 이런 것을 잘 고려해 달라 이 말씀으로 이해를 해 주시면 좋겠는데요.   일단 3억 이것은 증액하는 것으로 반영하겠습니다.   이것은 증액해서 올라온 게 아니라 추가 증액으로 요구한 건가요? 예, 그렇습니다. 위원님들이 의견을 주신 사항이 되겠습니다. 그런데 왜 그것을 그동안 반영 안 해서 올라왔어요, 사무처에서 안을 만들 때? 이것은 사실 KTX하고 할인제 폐지가 아직도 논의 중에 있습니다. 그래서 사실 실무자들은 아직 공개할 단계가 아니라고 그러는데 일단 국회에서도 방침을 할인제를 폐지하는 쪽으로 가닥을 잡아 가고 있는 것 같아서 말씀을 드렸는데요. 그런데 만약에 폐지한다고 그러면…… 일반 행정기관들도 할인율을 할 텐데, 안 해요? 아닙니다. 군인들 외에는 지금…… 그렇게 합시다. 국회만 그런 것을 할인해 달라고 하는 게 맞지 않네요. 3억은 현상 유지이지 의원님들한테 나가는 비용이 더 늘어나거나 이런 개념은 아니라고 보시면 됩니다. 의원 한 분당 1년에 얼마 더 추가 지급이 되나요, 단일선거구인 데는? 8페이지에 보시면 3곳인 경우에는 11개 지역구에 4200만 원이 추가된다는 거고요. 그러면 11로 나누면 되는 거지요? 예, 11로 나누면 됩니다. 계산기 있으면 저기 한번 해 봐요. 3곳인 경우가 386만 원입니다. 1년에? 예.  그다음에 4곳인 경우에는 770만 원, 5곳인 경우에는 1100만 원. 예를 들면 충남 논산이다 그러면 611만 원 더하기 삼백몇십만 원 해서 배정한다는 것이지요? 그렇습니다. 현재 예산보다 10% 정도 더 올리자는 건가요, 지금? 예, 10% 범위 내에서 올린 겁니다. 본인이 어떻게 그렇게 달라고 하겠습니까?  그런 애로사항을 많이 겪고 있는 것으로 알고 있습니다. 만약에 여기서 의결이 되면 예결위에 가서 설명 자료 할 때는 두 개를 묶어서 같이 해도 될 것 같습니다.   의원님들 국내출장 여비 이러저러한 사유로 해서 4억 3500이 필요하다 이렇게 하면 쉬울 거고, 분류를 하니까 조금…… 제가 한 마디만 더 드리겠습니다.  지금 이게 광역도별로 해 놨는데 약간 합리적이지 못한 것 같아요.  왜냐하면 예를 들면 강원도라 하더라도 사실은 충남 보령ㆍ서천 이쪽하고 강원도, 제일 가까운 데가 원주입니까? 비교해 보면 사실은 거리로 따지면, 교통비나 이런 걸 따지면 실제로는 충남 보령 출신 국회의원이 훨씬 더 들어가거든요. 그러니까 이것을 합리적으로 하려면 30㎞, 50㎞, 100㎞, 150㎞, 200㎞ 이렇게 나눠 주는 게 저는 오히려 더 합리적이라고 보거든요. 위원님, 단순 거리로만 보면 위원님 지적이 타당하신데요, 강원도 같은 경우에는 철도가 안 들어가는 데가 좀 있고 그래서 그 철도 안 들어가는 데는 저희가 비중을 좀 더 뒀습니다, 강원도 쪽에. 제가 먼저 말씀 좀 드릴까요.  일단 교섭단체가 늘어났지요. 또 최근에 바른정당이 교섭단체 자격을 상실하기도 했고. 그래서 일정 부분 증액의 필요성이 있다고는 생각이 되지만 송 위원님이 제시하신 정도의 증액 규모는 너무 큰 것 아닌가…… 그래서 사무처에서 예산을 짤 때 잡은 2억 3000 증액도 나름대로 그런 것들을 감안해서 한 건지를 한번 설명을 해 주셨으면 좋겠고요.  그다음에 정책위의장 특수활동비는 송옥주 위원님이 새롭게 3억 3700을 신규로 순증했는데 이 부분은 지금 사회적인 분위기나 이런 걸 봐서도 전혀 설득력이 없고 비난을 받을 수도 있는 거라고 생각돼서 일단 저는 정책위의장 특수활동비 신규 순증하는 것 이것은 없애야 되지 않나 하는 말씀을 하고.   그러면 얼마를 증가시켜야 되느냐의 문제인데 송 위원님 안이 14억 500만 원인데 그중 3억 3000을 뺀 나머지 중에 어느 정도를 할 거냐인데 일단 사무처에서 2억 3000을 증액할 때 이런 부분을 고려한 건지에 대한 보고를 한번 해 주셨으면 좋겠습니다. 사무처에서 2억 3000 증액을 할 때도 교섭단체가 1개 늘어남에 따른 추가 소요를 반영한 것은 맞습니다.   다만 2개에서 3개로 늘어날 때, 그러니까 작년도에 재작년에 비해서 1개 교섭단체가 늘어났거든요. 그때 사실은 충분히, 그러니까 말하자면 종래에 비해서 2개에서 3개 늘어난다고 하면 50%를 증액해야 되는데 그때 사실 한 반 정도밖에 증액을 안 했었습니다. 실제로 교섭단체 1개 늘어남에 따른 충분한 수요를 반영을 안 하고 50% 남짓 이렇게 반영을 했었기 때문에 저희들이 만약에 이번에 2억 3000을 증액한다 그래도 사실은 종래에 2개에서 3개 늘어날 때 예산을 추가 반영하는 그 수준에 맞춰서 증액했다고 보시면 될 것 같습니다. 정책간담회가 말 그대로 각 당의 정책위가 외부전문가들 토론회나 간담회나 이런 게 제가 보기에는 오히려 정책 활동을 촉진하는 데 필요한 비용 아닌가요? 자칫 운영비라든가 정책지원비라든가 특수활동비는 이게 그냥 너무 편의적으로 사용할 수 있다라고 하는 그런 오해 내지는 불신을 살 수 있는 여지가 있다면 정책간담회나 자료조사비는 좀 더 증액을 해도 그건 어차피 영수증 처리를 다 할 거고 계획서를 제출해서 나중에 확인할 것 아닌가요? 이런 것은 좀 더 증액을 해도 괜찮지 않나요? 이 정책간담회나 자료조사비는 사실, 자료조사비는 2016년도 그다음에 정책간담회는 2017년도에 신규로 반영된 건데요. 이거는 교섭단체 수하고는 관계없는 정책위 정책위원들 있지 않습니까? 그런 것들이니까 사실 이 부분은 위원장님 말씀대로 일정 부분 늘려도 정책 개발하는 데 충분히 도움이 될 것 같습니다. 올해 이 예산 사용 현황이 어떤가요? 한 40% 정도 현재 집행됐습니다. 많이 남았어요? 왜 이렇게 정책위들이 일을 안 하시나?  연말에 집행해요? 연말에 집행들을 많이 한다고 하니까……  어떻게 할까요? 그러면 여기를 좀 더 증액을, 어느 정도 선에서 하면 좋을까요? 한 5000, 3000 이렇게 증액시켜 주시면…… 그러면 1억, 6000, 이렇게 하자는 얘기지요? 예.",
"context_learn":"정책간담회와 자료조사비는 정책 활동을 촉진하는 데 필요한 비용으로 인식되며, 영수증 처리와 계획서 제출을 통한 투명한 운영이 이루어지고 있습니다. 일부 주장에 따르면, 교섭단체의 수 변화와 무관하게 정책위원들의 정책 개발 활동을 지원하기 위해 이 비용의 증액이 필요하다는 의견이 제시되었습니다. 현재, 정책간담회와 자료조사비 집행 현황은 연말에 대부분 사용되는 경향이 있기에, 사용률이 저조한 것처럼 보이더라도 실제로는 필요한 자금이 될 수 있습니다. 따라서, 추가적인 증액이 검토되고 있으며, 이것은 투명성과 효율성을 유지하면서 정책활동을 효과적으로 지원하기 위한 조치로 볼 수 있습니다. 이러한 자금이 어떻게 효과적으로 활용되고 투명하게 관리될 것인지에 대한 고려는 여전히 중요한 사항으로 남아 있으며, 정책 간담회와 자료조사비에 대해 어느 정도의 증액이 적절할지는 이러한 고려 사항을 바탕으로 결정될 것입니다.",
"context_summary":{"summary_q":"정책간담회와 자료조사비가 정책 활동을 촉진하는 데 필요한 비용으로 인식되고 있으며, 이러한 비용에 대한 증액이 필요하다는 주장이 있습니다. 현재 정책간담회와 자료조사비는 영수증 처리와 계획서 제출을 통해 투명하게 운영되고 있다는데, 이에 대한 추가적인 증액이 가능한지, 그리고 그로 인한 투명성과 효율성에 대한 고려는 어떻게 이루어지고 있나요?",
"summary_a":"정책간담회와 자료조사비는 정책 활동을 지원하는 데 필요한 비용으로 인식되고 있으며, 영수증 처리와 계획서 제출을 통해 투명하게 운영되고 있습니다. 추가적인 증액 가능성과 효율성, 투명성에 대한 고려는 현재 검토 중이며, 교섭단체 수와 관계없는 정책위원들을 고려하여 일부 증액이 필요할 수 있을 것으로 보입니다."},
"questioner_name":"박홍근",
"questioner_ID":"7465",
"questioner_ISNI":"0000000463654829",
"questioner_affiliation":"",
"questioner_position":"소위원장",
"question":{"tag":"455",
"comment":"정책간담회가 말 그대로 각 당의 정책위가 외부전문가들 토론회나 간담회나 이런 게 제가 보기에는 오히려 정책 활동을 촉진하는 데 필요한 비용 아닌가요? 자칫 운영비라든가 정책지원비라든가 특수활동비는 이게 그냥 너무 편의적으로 사용할 수 있다라고 하는 그런 오해 내지는 불신을 살 수 있는 여지가 있다면 정책간담회나 자료조사비는 좀 더 증액을 해도 그건 어차피 영수증 처리를 다 할 거고 계획서를 제출해서 나중에 확인할 것 아닌가요? 이런 것은 좀 더 증액을 해도 괜찮지 않나요?",
"keyword":"정책간담회,  증액,  정책위,  외부전문가들,  토론회,  간담회"},
"answerer_name":"장대섭",
"answerer_ID":" ",
"answerer_ISNI":" ",
"answerer_affiliation":"국회사무처",
"answerer_position":"기획조정실장",
"answer":{"tag":"456",
"comment":"이 정책간담회나 자료조사비는 사실, 자료조사비는 2016년도 그다음에 정책간담회는 2017년도에 신규로 반영된 건데요. 이거는 교섭단체 수하고는 관계없는 정책위 정책위원들 있지 않습니까? 그런 것들이니까 사실 이 부분은 위원장님 말씀대로 일정 부분 늘려도 정책 개발하는 데 충분히 도움이 될 것 같습니다.",
"keyword":"정책간담회,  자료조사비,  신규,  반영"}}